Metadata-Version: 2.1
Name: releaselogparser
Version: 1.0.1
Summary: Release log parser.
Home-page: http://git.gnu.org.ua/cgit/releaselogparser.git/
Author: Sergey Poznyakoff
Author-email: gray@gnu.org
License: GPL License
Keywords: release log history changes news
Platform: any
Classifier: Development Status :: 4 - Beta
Classifier: Intended Audience :: Developers
Classifier: License :: OSI Approved :: GNU General Public License (GPL)
Classifier: Operating System :: OS Independent
Classifier: Programming Language :: Python
Classifier: Topic :: Software Development :: Libraries :: Python Modules
Classifier: Topic :: Text Processing :: General
